flask_log_viewer/static/js/ansi_html.js
flask_log_viewer/templates/viewer.html
flask_log_viewer/viewer.py
flask_log_viewer-0.2.2.dist-info/LICENSE
flask_log_viewer-0.2.2.dist-info/METADATA
flask_log_viewer-0.2.2.dist-info/WHEEL
flask_log_viewer-0.2.2.dist-info/RECORD
