Metadata-Version: 2.1
Name: flask-log-viewer
Version: 0.2.2
Summary: Real time log viewer for flask applications
Home-page: https://github.com/thevgergroup/flask-log-viewer
License: MIT
Keywords: flask,log,viewer,tail,logviewer,log-viewer,log-tail,logtail,log-tailer,htmx
Author: patrick o'leary
Author-email: pjaol@pjaol.com
Requires-Python: >=3.11,<4.0
Classifier: Framework :: Flask
Classifier: License :: OSI Approved :: MIT License
Classifier: Programming Language :: Python :: 3
Classifier: Programming Language :: Python :: 3.11
Classifier: Programming Language :: Python :: 3.12
Classifier: Topic :: Internet :: WWW/HTTP :: WSGI :: Application
Classifier: Topic :: System :: Logging
Requires-Dist: flask (>=3.0.1,<4.0.0)
Requires-Dist: gevent (>=23.9.1,<24.0.0)
Requires-Dist: gunicorn (>=21.2.0,<22.0.0)
Requires-Dist: pygtail (>=0.14.0,<0.15.0)
Project-URL: Repository, https://github.com/thevgergroup/flask-log-viewer.git
